CHANGELOG.md
LICENSE
MANIFEST.in
README.rst
setup.py
Mopidy_Moped.egg-info/PKG-INFO
Mopidy_Moped.egg-info/SOURCES.txt
Mopidy_Moped.egg-info/dependency_links.txt
Mopidy_Moped.egg-info/entry_points.txt
Mopidy_Moped.egg-info/not-zip-safe
Mopidy_Moped.egg-info/requires.txt
Mopidy_Moped.egg-info/top_level.txt
mopidy_moped/__init__.py
mopidy_moped/ext.conf
mopidy_moped/static/index.html
mopidy_moped/static/assets/moped-0.7.1.js
mopidy_moped/static/assets/css/moped-0.7.1.css
mopidy_moped/static/assets/fonts/glyphicons-halflings-regular.eot
mopidy_moped/static/assets/fonts/glyphicons-halflings-regular.svg
mopidy_moped/static/assets/fonts/glyphicons-halflings-regular.ttf
mopidy_moped/static/assets/fonts/glyphicons-halflings-regular.woff
mopidy_moped/static/assets/fonts/glyphicons-halflings-regular.woff2
mopidy_moped/static/assets/images/ajax-loader.gif
mopidy_moped/static/assets/images/android-chrome-144x144.png
mopidy_moped/static/assets/images/android-chrome-192x192.png
mopidy_moped/static/assets/images/android-chrome-36x36.png
mopidy_moped/static/assets/images/android-chrome-48x48.png
mopidy_moped/static/assets/images/android-chrome-72x72.png
mopidy_moped/static/assets/images/android-chrome-96x96.png
mopidy_moped/static/assets/images/apple-touch-icon-114x114.png
mopidy_moped/static/assets/images/apple-touch-icon-120x120.png
mopidy_moped/static/assets/images/apple-touch-icon-144x144.png
mopidy_moped/static/assets/images/apple-touch-icon-152x152.png
mopidy_moped/static/assets/images/apple-touch-icon-180x180.png
mopidy_moped/static/assets/images/apple-touch-icon-57x57.png
mopidy_moped/static/assets/images/apple-touch-icon-60x60.png
mopidy_moped/static/assets/images/apple-touch-icon-72x72.png
mopidy_moped/static/assets/images/apple-touch-icon-76x76.png
mopidy_moped/static/assets/images/apple-touch-icon-precomposed.png
mopidy_moped/static/assets/images/apple-touch-icon.png
mopidy_moped/static/assets/images/browserconfig.xml
mopidy_moped/static/assets/images/favicon-16x16.png
mopidy_moped/static/assets/images/favicon-32x32.png
mopidy_moped/static/assets/images/favicon-96x96.png
mopidy_moped/static/assets/images/favicon.ico
mopidy_moped/static/assets/images/library-icon.png
mopidy_moped/static/assets/images/manifest.json
