Metadata-Version: 1.1
Name: Mopidy-Moped
Version: 0.7.1
Summary: Responsive Web client for Mopidy
Home-page: https://github.com/martijnboland/moped
Author: Martijn Boland
Author-email: martijn@boland.org
License: MIT License
Platform: UNKNOWN
Classifier: Development Status :: 4 - Beta
Classifier: Environment :: No Input/Output (Daemon)
Classifier: Intended Audience :: End Users/Desktop
Classifier: License :: OSI Approved :: MIT License
Classifier: Operating System :: OS Independent
Classifier: Programming Language :: Python :: 2
Classifier: Topic :: Multimedia :: Sound/Audio :: Players
